Metadata-Version: 1.1
Name: Hi-Aviv
Version: 0.0.2
Summary: Hi Aviv is the personal assistant for your computer!
Home-page: UNKNOWN
Author: aviv05423
Author-email: avivb60@gmail.com
License: MIT
Keywords: assistant,Aviv,personal assistant,Voice assistant,Virtual Assistant
Platform: UNKNOWN
Classifier: Development Status :: 5 - Production/Stable
Classifier: Intended Audience :: Education
Classifier: Operating System :: Microsoft :: Windows :: Windows 10
Classifier: License :: OSI Approved :: MIT License
Classifier: Programming Language :: Python :: 3
